{
  "channel_name": "Concessa Obvius",
  "channel_id": "UCxxxxxxxxxxxxxxxxxxxxxxxxxx",
  "api_key": "",
  "credentials_file": "",
  "auto_respond_enabled": true,
  "response_templates": {
    "question": "Thank you for the question! Here are some resources that might help:\n- Check our FAQ: [link to FAQ]\n- Getting started guide: [link]\n- Feel free to reply with more questions!",
    "praise": "Thank you so much for the kind words! We really appreciate your support and feedback. 😊"
  },
  "review_category": "sales",
  "log_file": ".cache/youtube-comments.jsonl",
  "stats_file": ".cache/youtube-monitor-stats.jsonl",
  "max_comments_per_run": 50,
  "check_interval_minutes": 30
}
